CHANGELOG.txt
LICENCE.txt
MANIFEST.in
README.md
README.txt
setup.py
acceldata_airflow_sdk/__init__.py
acceldata_airflow_sdk/dag.py
acceldata_airflow_sdk/initialiser.py
acceldata_airflow_sdk.egg-info/PKG-INFO
acceldata_airflow_sdk.egg-info/SOURCES.txt
acceldata_airflow_sdk.egg-info/dependency_links.txt
acceldata_airflow_sdk.egg-info/requires.txt
acceldata_airflow_sdk.egg-info/top_level.txt
acceldata_airflow_sdk/decorators/__init__.py
acceldata_airflow_sdk/decorators/handle_callback.py
acceldata_airflow_sdk/decorators/job.py
acceldata_airflow_sdk/decorators/span.py
acceldata_airflow_sdk/operators/__init__.py
acceldata_airflow_sdk/operators/execute_policy_operator.py
acceldata_airflow_sdk/operators/job_operator.py
acceldata_airflow_sdk/operators/span_operator.py
acceldata_airflow_sdk/operators/torch_initialiser_operator.py
acceldata_airflow_sdk/utils/__init__.py
acceldata_airflow_sdk/utils/airflow_job_utils.py
acceldata_airflow_sdk/utils/callback.py
acceldata_airflow_sdk/utils/torch_client.py
adoc_listener_plugin/README.md
adoc_listener_plugin/plugins/__init__.py
adoc_listener_plugin/plugins/listener_plugin.py
adoc_listener_plugin/plugins/listener/__init__.py
adoc_listener_plugin/plugins/listener/constants.py
adoc_listener_plugin/plugins/listener/events_listener.py
adoc_listener_plugin/plugins/listener/utils.py
docs/conf.py
docs/_build/html/_sources/index.rst.txt
docs/_build/html/_sources/modules.rst.txt
docs/_build/html/_sources/torch_airflow_sdk.decorators.rst.txt
docs/_build/html/_sources/torch_airflow_sdk.operators.rst.txt
docs/_build/html/_sources/torch_airflow_sdk.rst.txt
docs/_build/html/_sources/torch_airflow_sdk.utils.rst.txt
openlineage/airflow_local_settings.py
openlineage/config/__init__.py
openlineage/extractors/__init__.py
openlineage/extractors/bigquery_insert_job_extractor.py
openlineage/extractors/gcs_bigquery_extractor.py
openlineage/policy/__init__.py
openlineage/policy/config_helper.py
openlineage/tokenproviders/__init__.py
openlineage/tokenproviders/access_key_secret_token_provider.py
openlineage/tokenproviders/access_key_secret_token_provider_v1merck.py
test_dags/execute_policy_operator_dag.py
test_dags/job_deco_failure_dag_2_retries.py
